pycafee/__init__.py
pycafee/version.py
pycafee/data/__init__.py
pycafee/data/main_database.db
pycafee/database_management/__init__.py
pycafee/database_management/management.py
pycafee/functions/__init__.py
pycafee/functions/functions.py
pycafee/normalitycheck/__init__.py
pycafee/normalitycheck/abdimolin.py
pycafee/normalitycheck/andersondarling.py
pycafee/normalitycheck/comparison.py
pycafee/normalitycheck/densityplot.py
pycafee/normalitycheck/dotplot.py
pycafee/normalitycheck/kolmogorovsmirnov.py
pycafee/normalitycheck/lilliefors.py
pycafee/normalitycheck/normalitycheck.py
pycafee/normalitycheck/shapirowilk.py
pycafee/sample/__init__.py
pycafee/sample/sample.py
pycafee/sample/studentdistribution.py
pycafee/utils/__init__.py
pycafee/utils/checkers.py
pycafee/utils/general.py
pycafee/utils/helpers.py
tests/__init__.py
tests/database_management/__init__.py
tests/database_management/test_management/__init__.py
tests/database_management/test_management/test__connecting_to_database.py
tests/database_management/test_management/test__get_all_available_languages.py
tests/database_management/test_management/test__get_all_languages_for_func.py
tests/database_management/test_management/test__get_current_default_language.py
tests/database_management/test_management/test__get_messages.py
tests/database_management/test_management/test__query_func_id.py
tests/database_management/test_management/test__set_default_language.py
tests/database_management/test_management/test_display_all_available_languages.py
tests/database_management/test_management/test_display_current_default_language.py
tests/functions/__init__.py
tests/functions/functions/__init__.py
tests/functions/functions/test_multimode.py
tests/normalitycheck/__init__.py
tests/normalitycheck/AbdiMolin/__init__.py
tests/normalitycheck/AbdiMolin/test_draw_critical_values.py
tests/normalitycheck/AbdiMolin/test_fit.py
tests/normalitycheck/AbdiMolin/test_fn_abdi_molin.py
tests/normalitycheck/AbdiMolin/test_get_critical_value.py
pycafee-0.0.13.dist-info/METADATA
pycafee-0.0.13.dist-info/WHEEL
pycafee-0.0.13.dist-info/top_level.txt
pycafee-0.0.13.dist-info/RECORD
