Metadata-Version: 2.1
Name: pycafee
Version: 0.0.13
Summary: A package to make scientific research easier
Home-page: https://github.com/pycafee/pycafee
Author: Anderson Marcos Dias Canteli
Author-email: andersonmdcanteli@gmail.com
License: UNKNOWN
Keywords: statistics,sample analisys
Platform: UNKNOWN
Classifier: Development Status :: 3 - Alpha
Classifier: Programming Language :: Python :: 3.8
Classifier: Programming Language :: Python :: 3.7
Classifier: Programming Language :: Python :: 3 :: Only
Classifier: License :: OSI Approved :: GNU General Public License v3 (GPLv3)
Requires-Python: >=3.7, <3.9
Requires-Dist: colorama (==0.4.4)
Requires-Dist: matplotlib (==3.2.2)
Requires-Dist: numpy (==1.21.6)
Requires-Dist: openpyxl (==3.0.10)
Requires-Dist: pandas (==1.3.5)
Requires-Dist: scipy (==1.4.1)
Requires-Dist: statsmodels (==0.11.0)
Requires-Dist: tabulate (==0.8.9)
